essx/README.md
essx/__init__.py
essx/__version__.py
essx/essx.py
essx/examples/demo.py
essx-0.0.0a0.dist-info/METADATA
essx-0.0.0a0.dist-info/WHEEL
essx-0.0.0a0.dist-info/top_level.txt
essx-0.0.0a0.dist-info/RECORD
