Metadata-Version: 2.1
Name: essx
Version: 0.0.0a0
Summary: A data science package for data movement and transformation
Author: StreamSets, Inc.
Classifier: Development Status :: 2 - Pre-Alpha
Classifier: Programming Language :: Python :: 3.10
Classifier: Programming Language :: Python :: 3.11
Classifier: Programming Language :: Python :: 3.12
Requires-Python: >=3.10
Requires-Dist: streamsets ==6.0.1
Requires-Dist: pymysql ==0.10.1
Requires-Dist: pandas ==1.5.3
Requires-Dist: snowflake-connector-python ==2.9.0
